love_lines/__init__.py
love_lines/llgenerator.py
love_lines-0.1.0.dist-info/licenses/LICENSE
love_lines-0.1.0.dist-info/METADATA
love_lines-0.1.0.dist-info/WHEEL
love_lines-0.1.0.dist-info/top_level.txt
love_lines-0.1.0.dist-info/RECORD
