Metadata-Version: 2.4
Name: love_lines
Version: 0.1.0
Summary: A sweet library that gives you beautiful love lines ❤️
Home-page: https://github.com/brooklynwidz/love_lines
Author: Brooklyn widz
License: MIT
Classifier: Programming Language :: Python :: 3
Classifier: License :: OSI Approved :: MIT License
Classifier: Operating System :: OS Independent
Classifier: Topic :: Text Processing :: Linguistic
Requires-Python: >=3.6
License-File: LICENSE
Dynamic: author
Dynamic: classifier
Dynamic: description
Dynamic: description-content-type
Dynamic: home-page
Dynamic: license
Dynamic: license-file
Dynamic: requires-python
Dynamic: summary
